chipstream/__init__.py
chipstream/_version.py
chipstream/path_cache.py
chipstream/cli/__init__.py
chipstream/cli/__main__.py
chipstream/cli/_main.py
chipstream/cli/cli_common.py
chipstream/cli/cli_main.py
chipstream/cli/cli_proc.py
chipstream/cli/cli_valid.py
chipstream/gui/__init__.py
chipstream/gui/__main__.py
chipstream/gui/_main.py
chipstream/gui/dlg_model_props.py
chipstream/gui/dlg_model_props.ui
chipstream/gui/main_window.py
chipstream/gui/main_window.ui
chipstream/gui/manager.py
chipstream/gui/splash.py
chipstream/gui/table_progress.py
chipstream/gui/img/chipstream_icon.png
chipstream-0.9.14.dist-info/licenses/LICENSE
chipstream-0.9.14.dist-info/METADATA
chipstream-0.9.14.dist-info/WHEEL
chipstream-0.9.14.dist-info/entry_points.txt
chipstream-0.9.14.dist-info/top_level.txt
chipstream-0.9.14.dist-info/RECORD
