Metadata-Version: 2.4
Name: chipstream
Version: 0.9.14
Summary: GUI and CLI for DC data postprocessing
Author: Paul Müller
Maintainer-email: Paul Müller <dev@craban.de>
License-Expression: GPL-3.0-or-later
Project-URL: source, https://github.com/DC-Analysis/ChipStream
Project-URL: tracker, https://github.com/DC-Analysis/ChipStream/issues
Project-URL: documentation, https://chipstream.readthedocs.io/en/stable/
Project-URL: changelog, https://chipstream.readthedocs.io/en/stable/sec_changelog.html
Keywords: RT-DC,deformability,cytometry
Classifier: Operating System :: OS Independent
Classifier: Programming Language :: Python :: 3
Classifier: Topic :: Scientific/Engineering :: Visualization
Classifier: Intended Audience :: Science/Research
Requires-Python: <4,>=3.10
License-File: LICENSE
Requires-Dist: dcnum>=0.29.1
Requires-Dist: h5py<4,>=3.0.0
Requires-Dist: numpy<3,>=1.21
Requires-Dist: psutil>=7
Provides-Extra: all
Requires-Dist: chipstream[cli,gui,torch]; extra == "all"
Provides-Extra: cli
Requires-Dist: click>=8.2; extra == "cli"
Provides-Extra: gui
Requires-Dist: pyqt6; extra == "gui"
Provides-Extra: torch
Requires-Dist: torch>=2.2; extra == "torch"
Dynamic: license-file
